dataconcat/data/Issam Alnajjar.csv
dataconcat/data/Issam Alnajjar1.csv
dataconcat/data/Issey Cross.csv
dataconcat/data/Issey Cross1.csv
dataconcat/data/John R. Miller.csv
dataconcat/data/John R. Miller1.csv
dataconcat/data/Laufey.csv
dataconcat/data/Laufey1.csv
dataconcat/data/Londin Thompson.csv
dataconcat/data/Londin Thompson1.csv
dataconcat/data/LØLØ.csv
dataconcat/data/LØLØ1.csv
dataconcat/mixer.py
dataconcat/simplicity.csv
dataconcat-0.1.2.dist-info/entry_points.txt
dataconcat-0.1.2.dist-info/WHEEL
dataconcat-0.1.2.dist-info/METADATA
dataconcat-0.1.2.dist-info/RECORD
