Metadata-Version: 2.1
Name: dataconcat
Version: 0.1.2
Summary: 
Author: Kevin Hill
Author-email: kah.kevin.hill@gmail.com
Requires-Python: >=3.9,<4.0
Classifier: Programming Language :: Python :: 3
Classifier: Programming Language :: Python :: 3.9
Requires-Dist: maya (>=0.6.1,<0.7.0)
Requires-Dist: pandas (>=1.2.4,<2.0.0)
Requires-Dist: pandera (>=0.6.4,<0.7.0)
Requires-Dist: toolz (>=0.11.1,<0.12.0)
Requires-Dist: typer[all] (>=0.3.2,<0.4.0)
